LICENSE
MANIFEST.in
README.md
setup.py
GCNFrame/Biodata.py
GCNFrame/GCNmodel.py
GCNFrame/__init__.py
GCNFrame/encode_seq.c
GCNFrame/encode_seq.cpython-38-darwin.so
GCNFrame/encode_seq.cpython-38-x86_64-linux-gnu.so
GCNFrame/encode_seq.pyx
GCNFrame/setup.py
GCNFrame/version.py
GCNFrame.egg-info/PKG-INFO
GCNFrame.egg-info/SOURCES.txt
GCNFrame.egg-info/dependency_links.txt
GCNFrame.egg-info/not-zip-safe
GCNFrame.egg-info/requires.txt
GCNFrame.egg-info/top_level.txt
GCNFrame/__pycache__/Biodata.cpython-310.pyc
GCNFrame/__pycache__/Biodata.cpython-38.pyc
GCNFrame/__pycache__/GCNmodel.cpython-38.pyc
GCNFrame/__pycache__/__init__.cpython-310.pyc
GCNFrame/__pycache__/__init__.cpython-38.pyc
GCNFrame/build/lib.macosx-10.9-x86_64-cpython-38/encode_seq.cpython-38-darwin.so
GCNFrame/build/temp.linux-x86_64-3.8/encode_seq.o
GCNFrame/build/temp.macosx-10.9-x86_64-cpython-38/encode_seq.o