Metadata-Version: 2.1
Name: GCNFrame
Version: 0.1.2
Summary: This is a python package for genomics study with a GCN framework.
Home-page: https://github.com/deepomicslab/GCNFrame
Author: WANG Ruohan
Author-email: ruohawang2-c@my.cityu.edu.hk
License: MIT
Classifier: License :: OSI Approved :: MIT License
Classifier: Programming Language :: Python :: 3.8
Requires-Python: >=3.8
License-File: LICENSE
